btfxwss/__init__.py
btfxwss/client.py
btfxwss/configs.py
btfxwss/connection.py
btfxwss/queue_processor.py
btfxwss-1.2.3.dist-info/DESCRIPTION.rst
btfxwss-1.2.3.dist-info/METADATA
btfxwss-1.2.3.dist-info/RECORD
btfxwss-1.2.3.dist-info/WHEEL
btfxwss-1.2.3.dist-info/metadata.json
btfxwss-1.2.3.dist-info/top_level.txt
