Metadata-Version: 2.0
Name: btfxwss
Version: 1.2.3
Summary: Python 3.5+ Websocket Client for the Bitfinex WSS API.
Home-page: https://github.com/nlsdfnbch/bitfinex_wss
Author: Nils Diefenbach
Author-email: nlsdfnbch.foss@kolabnow.com
License: MIT
Platform: UNKNOWN
Requires-Dist: websocket-client
